[   {
          "text": "Συμπλήρωσε τις λέξεις βάζοντας σύμβολα ή αριθμούς",
          "image" : "images/b_07/symvola-ari8moi/01-Mpravo.png",
          "answer" : "Μπράβο!!!",
          "hints" : "0,3,4,5",
          "disabled_hints" : "yes"
    },
    {
          "text": "Συμπλήρωσε τις λέξεις βάζοντας σύμβολα ή αριθμούς",
          "image" : "images/b_07/symvola-ari8moi/02-Stars.png",
          "answer" : "Stars***",
          "hints" : "0,1,2,3,4",
          "disabled_hints" : "yes"
    },
    {
          "text": "Συμπλήρωσε τις λέξεις βάζοντας σύμβολα ή αριθμούς",
          "image" : "images/b_07/symvola-ari8moi/04-Three.png",
          "answer" : "Τρία(3)",
          "hints" : "0,1,2,3",
          "disabled_hints" : "yes"
    },
    {
          "text": "Συμπλήρωσε τις λέξεις βάζοντας σύμβολα ή αριθμούς",
          "image" : "images/b_07/symvola-ari8moi/05-teacher-sxoleio-pw.png",
          "answer" : "teacher@sxoleio.pw",
          "hints" : "1,2,3,4,5,6,8,9,10,11,12,13,14,16,17",
          "disabled_hints" : "yes"
    },
    {
          "text": "Συμπλήρωσε τις λέξεις βάζοντας σύμβολα ή αριθμούς",
          "image" : "images/b_07/symvola-ari8moi/06-Numbers.png",
          "answer" : "1234567890",
          "hints" : "2,7,9,10,14,18,19",
          "disabled_hints" : "yes"
    },
    {
          "text": "Συμπλήρωσε τις λέξεις βάζοντας σύμβολα ή αριθμούς",
          "image" : "images/b_07/symvola-ari8moi/07-Dollar.png",
          "answer" : "Δολλάριο$",
          "hints" : "1,2,3,4,5,6,7",
          "disabled_hints" : "yes"
    },
    {
          "text": "Συμπλήρωσε τις λέξεις βάζοντας σύμβολα ή αριθμούς",
          "image" : "images/b_07/symvola-ari8moi/08-Hash.png",
          "answer" : "Δίεση#",
          "hints" : "0,2,3,4",
          "disabled_hints" : "yes"
    },
    {
          "text": "Συμπλήρωσε τις λέξεις βάζοντας σύμβολα ή αριθμούς",
          "image" : "images/b_07/symvola-ari8moi/09-at.png",
          "answer" : "Παπάκι@",
          "hints" : "1,2,4,5",
          "disabled_hints" : "yes"
    },
    {
          "text": "Συμπλήρωσε τις λέξεις βάζοντας σύμβολα ή αριθμούς",
          "image" : "images/b_07/symvola-ari8moi/10-Kapelaki.png",
          "answer" : "Καπελάκι^",
          "hints" : "1,2,3,4,5,6,7",
          "disabled_hints" : "yes"
    },
    {
          "text": "Συμπλήρωσε τις λέξεις βάζοντας σύμβολα ή αριθμούς",
          "image" : "images/b_07/symvola-ari8moi/11-Percent.png",
          "answer" : "Επί τοις εκατό%",
          "hints" : "1,2,3,4,5,6,7,8,9,10,12,13",
          "disabled_hints" : "yes"
    },
    {
          "text": "Συμπλήρωσε τις λέξεις βάζοντας σύμβολα ή αριθμούς",
          "image" : "images/b_07/symvola-ari8moi/12-Minus.png",
          "answer" : "Αφαίρεση-",
          "hints" : "1,2,3,5,6,7",
          "disabled_hints" : "yes"
    },
    {
          "text": "Συμπλήρωσε τις λέξεις βάζοντας σύμβολα ή αριθμούς",
          "image" : "images/b_07/symvola-ari8moi/13-Plus.png",
          "answer" : "Πρόσθεση+",
          "hints" : "1,2,4,5,6,7",
          "disabled_hints" : "yes"
    },
    {
          "text": "Συμπλήρωσε τις λέξεις βάζοντας σύμβολα ή αριθμούς",
          "image" : "images/b_07/symvola-ari8moi/14-Equal.png",
          "answer" : "Ίσον=",
          "hints" : "1,2,3",
          "disabled_hints" : "yes"
    }
]
